proxykit/__init__.py
proxykit/__main__.py
proxykit/constants.py
proxykit/core.py
proxykit/exceptions.py
proxykit/models.py
proxykit/utils.py
proxykit/validator.py
proxykit/loader/__init__.py
proxykit/loader/internal_loader.py
proxykit/loader/proxy_loader.py
proxykit/parser/__init__.py
proxykit/parser/base.py
proxykit/parser/csv_parser.py
proxykit/parser/ip_parser.py
proxykit/parser/json_parser.py
proxykit/parser/utils.py
proxykit/storage/__init__.py
proxykit/storage/appdirs_manager.py
proxykit/storage/cache_manager.py
proxykit-0.0.2.dist-info/licenses/AUTHORS.rst
proxykit-0.0.2.dist-info/licenses/LICENSE
proxykit-0.0.2.dist-info/METADATA
proxykit-0.0.2.dist-info/WHEEL
proxykit-0.0.2.dist-info/top_level.txt
proxykit-0.0.2.dist-info/RECORD
