Metadata-Version: 2.4
Name: proxykit
Version: 0.0.2
Summary: ProxyKit is a lightweight Python package for managing and rotating proxy servers, user agents, and headers. It validates proxy lists and provides a context manager to easily inject reliable, random configurations into your HTTP requests.
Author-email: Suraj Airi <surajairi.ml@gmail.com>
License: MIT license
Requires-Python: >=3.8
License-File: LICENSE
License-File: AUTHORS.rst
Requires-Dist: appdirs>=1.4.4
Requires-Dist: requests>=2.32.4
Requires-Dist: tqdm>=4.67.1
Dynamic: license-file
